minepy/__init__.py
minepy/main.py
minepy/minepy.py
elbert06_minepy-1.0.0.1.dist-info/METADATA
elbert06_minepy-1.0.0.1.dist-info/WHEEL
elbert06_minepy-1.0.0.1.dist-info/top_level.txt
elbert06_minepy-1.0.0.1.dist-info/RECORD
