Metadata-Version: 2.1
Name: elbert06-minepy
Version: 1.0.0.1
Summary: elbert06_minepy
Home-page: https://github.com/elbert06
Author: elbert
Author-email: elbert06@hanmail.net
License: MIT
Platform: UNKNOWN
Requires-Python: >=3
